etc/smartscheduler/config_example.cfg
smartsched/__init__.py
smartsched/common.py
smartsched/cloud_api/__init__.py
smartsched/cloud_api/base_cloud.py
smartsched/cloud_api/one_cloud.py
smartsched/cloud_api/one_constants.py
smartsched/monitoring_api/__init__.py
smartsched/monitoring_api/influx.py
smartsched-0.1.14.dist-info/METADATA
smartsched-0.1.14.dist-info/RECORD
smartsched-0.1.14.dist-info/WHEEL
smartsched-0.1.14.dist-info/top_level.txt
