Metadata-Version: 2.1
Name: smartsched
Version: 0.1.14
Summary: Basic library for allowing authomatic VMs deployment and migration for the purpose of optimisation.
Home-page: https://github.com/JINR-LIT/SmartScheduler-Core
Author: JINR LIT Cloud Team
Author-email: gavelock+jinr@gmail.com
License: UNKNOWN
Keywords: cloud api scheduler
Platform: UNKNOWN
Classifier: Development Status :: 3 - Alpha
Classifier: Intended Audience :: Developers
Classifier: Topic :: Software Development
Classifier: Programming Language :: Python :: 3
Classifier: Programming Language :: Python :: 3.3
Classifier: Programming Language :: Python :: 3.4
Classifier: Programming Language :: Python :: 3.5
Requires-Python: ~=3.4
Provides-Extra: dev
Requires-Dist: influxdb
Requires-Dist: xmltodict
Provides-Extra: dev
Requires-Dist: pytest; extra == 'dev'
Requires-Dist: pytest-pep8; extra == 'dev'
Requires-Dist: pytest-cov; extra == 'dev'
Requires-Dist: bumpversion; extra == 'dev'
Requires-Dist: wheel; extra == 'dev'
Requires-Dist: twine; extra == 'dev'
